xavier_utils/__init__.py
xavier_utils/connections/__init__.py
xavier_utils/connections/s3_connection.py
xavier_utils-0.0.6.dist-info/LICENSE
xavier_utils-0.0.6.dist-info/METADATA
xavier_utils-0.0.6.dist-info/WHEEL
xavier_utils-0.0.6.dist-info/top_level.txt
xavier_utils-0.0.6.dist-info/RECORD
