Metadata-Version: 2.1
Name: xavier-utils
Version: 0.0.6
Summary: Classes and functions to work with xavier app
Home-page: UNKNOWN
Author: Luigi Ferrari
License: 'MIT'
Platform: UNKNOWN
Classifier: Programming Language :: Python :: 3
Classifier: License :: OSI Approved :: MIT License
Classifier: Operating System :: OS Independent
License-File: LICENSE
